setup.py
dnsanalysis/__init__.py
dnsanalysis/bigramlib.py
dnsanalysis.egg-info/PKG-INFO
dnsanalysis.egg-info/SOURCES.txt
dnsanalysis.egg-info/dependency_links.txt
dnsanalysis.egg-info/not-zip-safe
dnsanalysis.egg-info/top_level.txt