Metadata-Version: 1.0
Name: dnsanalysis
Version: 0.1
Summary: Python DNS Analysis
Home-page: http://github.com/cyberfrost/dnsanalysis
Author: Enrico Hugo
Author-email: cyberfrost7@gmail.com
License: UNKNOWN
Platform: UNKNOWN
